[
  {
    "id": 1,
    "type": "logic",
    "question": "\"হায় আল্লাহ!  খালেদ ; আমি যদি দেশের প্রধানমন্ত্রী হতে পারতাম\" উক্তিটি কার হতে পারে?",
    "options": [
      "কাজী নজরুল",
      "নজরুল ইসলাম",
      "আসিফ নজরুল",
      "আপনি নিজেই"
    ],
    "answer": 3
  },
  {
    "id": 2,
    "type": "logic",
    "question": "আপনার ও আপনার পার্টনার এর মধ্যে ঝামেলা মিটাতে এখন সবথেকে কাকে বেশি প্রয়োজন?",
    "options": [
      "শাহিদ আফ্রিদি",
      "শাহিন আফ্রিদি",
      "মিরাজ আফ্রিদি",
      "তৌহিদ আফ্রিদি"
    ],
    "answer": 4
  },
  {
    "id": 3,
    "type": "logic",
    "question": "নিচের কোনটি একবিংশ শতাব্দির সেরা চরিত্র?",
    "options": [
      "ব্যাক্তি সাকিব",
      "রাজনৈতিক সাকিব",
      "ক্রিকেটার সাকিব",
      "জুয়ারি সাকিব"
    ],
    "answer": 1
  },
  {
    "id": 4,
    "type": "logic",
    "question": "Sensation এর স্বনামধন্য Brand Ambassador কে?",
    "options": [
      "Andrew Tate",
      "Dhon Cena",
      "Pori Moni",
      "Salman Muqtadir"
    ],
    "answer": 4
  },
  {
    "id": 5,
    "type": "logic",
    "question": "Dickবাজি দিতে উস্তাদ কে?",
    "options": [
      "সাকিব খান",
      "সালমান খান",
      "জায়েদ খান",
      "শাহরুখ খান"
    ],
    "answer": 3
  },
  {
    "id": 6,
    "type": "logic",
    "question": "ভাতের হোটেলের মালিক কে?",
    "options": [
      "মুকেশ আম্বানি",
      "হাউন আঙ্কেল",
      "ইলন মাস্ক",
      "রতন টাটা"
    ],
    "answer": 2
  },
  {
    "id": 7,
    "type": "logic",
    "question": "ক্রিস্টোফার নোলান তার নতুন সিনেমার জন্য নায়ক ও গায়ক উভয় গুণাবলী সম্পন্ন একজন অভিনেতা খুঁজছেন। নিচের কে সবথেকে বেস্ট চয়েজ?",
    "options": [
      "হিরো আলম",
      "নাম্বার 1 সাকিব খান",
      "আফরান নিশু",
      "আপনার Ex"
    ],
    "answer": 1
  },
  {
    "id": 8,
    "type": "logic",
    "question": "অসম্ভবকে সম্ভব করাই কার কাজ?",
    "options": [
      "চিংগাম",
      "জ্বলন্ত অলীল",
      "অনন্ত জলীল",
      "এন্ড্রু টেট"
    ],
    "answer": 3
  },
  {
    "id": 9,
    "type": "logic",
    "question": "লিঙ্গ ছাড়া সিংহ কে?",
    "options": [
      "সালমান খান",
      "এডল্ফ খান",
      "Andrew Tate",
      "আপনার বন্ধু!"
    ],
    "answer": 2
  },
  {
    "id": 10,
    "type": "logic",
    "question": "বাংলার পেপ Gandiওয়ালা কে?",
    "options": [
      "বাতেন",
      "রিফাত মাসুদ",
      "হাভিয়ের কাবরেরা",
      "Neyon & ON"
    ],
    "answer": 3
  },
  {
    "id": 11,
    "type": "logic",
    "question": "ময়ুখ রঞ্জন ঘোষ এর পেশা কী?",
    "options": [
      "মলম বিক্রেতা",
      "হকার",
      "হলুদ সাংবাদিক",
      "সবগুলোই"
    ],
    "answer": 4
  },
  {
    "id": 12,
    "type": "logic",
    "question": "পৃথিবীর সবথেকে অথেন্টিক এবং রিয়েল খবর প্রচার করে কোন টেলিভিশন?",
    "options": [
      "বাতাবি লেবু টেলিভিশন",
      "দৈনিক ওয়াদ্দাফাক",
      "আনোয়ার টিভি",
      "দিল্লি স্টার"
    ],
    "answer": 3
  },
  {
    "id": 13,
    "type": "logic",
    "question": "জনাব 'x' সোনালী হাঁস খুব পছন্দ করেন। তিনি বাড়ি ফেরার সময় প্রতিবার হাঁস নিয়ে ফিরেন। জনাব কে হতে পারেন?",
    "options": [
      "দ্যা গ্রিডি ফার্মার",
      "লিটন দাস",
      "রুমিন ফারহানা",
      "আসিফ মাহমুদ"
    ],
    "answer": 2
  },
  {
    "id": 14,
    "type": "logic",
    "question": "লর্ড উপাধির জন্য যোগ্য ব্যাক্তি কে?",
    "options": [
      "শান্ত",
      "লিটন দাস",
      "ভাত শামীম",
      "নাইম আলম"
    ],
    "answer": 1
  },
  {
    "id": 15,
    "type": "logic",
    "question": "নিচের কে সবচেয়ে বেশি সুন্দর?",
    "options": [
      "হানিয়া আমির",
      "দূরে ফিশান",
      "আপনার Ex",
      "গেম ডেভলপার এর Ex"
    ],
    "answer": 4
  },
  {
    "id": 16,
    "type": "logic",
    "question": "Xefer এর সোনা বন্ধুটি তাহলে কে ছিলো?",
    "options": [
      "রাফসান সাবাব",
      "প্রীতম হাসান",
      "MUZA",
      "সালমান মুক্তাদির"
    ],
    "answer": 1
  },
  {
    "id": 17,
    "type": "logic",
    "question": "নিচের কে ফুটবলের Greatest of All time?",
    "options": [
      "পেসি",
      "পেনালদো",
      "এন্টনি",
      "তারেক মনোয়ার"
    ],
    "answer": 4
  },
  {
    "id": 18,
    "type": "logic",
    "question": "দুগ্ধ-স্রোতরুপী তুমি জন্মভূমি স্তনে। চরণটি শুনে কার কথা মনে পড়ে?",
    "options": [
      "মুমতাহিনা",
      "সিডনী সুইনি",
      "কাপাতাক্ষ নদ",
      "মাইকেল মধুসুদন"
    ],
    "answer": 3
  },
  {
    "id": 19,
    "type": "logic",
    "question": "একজন শিক্ষার্থীর জীবনে সবচেয়ে বড় ভুল কোনটি?",
    "options": [
      "রিলেশনশিপে যাওয়া",
      "পড়ালেখা না করা",
      "Reels দেখা",
      "উদ্ভাসে গার্ডিয়েনের নম্বর দেওয়া"
    ],
    "answer": 4
  },
  {
    "id": 20,
    "type": "logic",
    "question": "\"মুরব্বি, মুরব্বি; উহূ উহূ!!\" এই উক্তিটি কার?",
    "options": [
      "মুশতাক ফয়েজী",
      "তাহেরী",
      "তারেক মনোয়ার",
      "আবরারুল হক আসিফ"
    ],
    "answer": 1
  },
  {
    "id": 21,
    "type": "logic",
    "question": "বাংলার ইতিহাস ও ঐতিহ্যে মিশে আছে হস্তশিল্প। আর যখনি হস্তশিল্পের কথা আসে মনে পড়ে বিখ্যাত কোন হস্তশিল্পীর কথা?",
    "options": [
      "সালমান খান",
      "ইমরান হাসমী",
      "সালমান মুক্তাদির",
      "মিরাজ আফ্রিদি"
    ],
    "answer": 4
  },
  {
    "id": 22,
    "type": "logic",
    "question": "The only person who owned the dialogue \"Legend never die\".",
    "options": [
      "Michael Jackson",
      "Diego Maradona",
      "Issac Newton",
      "Danish Zehen"
    ],
    "answer": 4
  },
  {
    "id": 23,
    "type": "logic",
    "question": "সবজিদের মধ্যে কে সবচেয়ে বেশি রুড ব্যবহার করে?",
    "options": [
      "শসা",
      "আলু",
      "লেবু",
      "টমেটো"
    ],
    "answer": 1
  },
  {
    "id": 24,
    "type": "logic",
    "question": "নিচের কোন কাজটি ঈদের দিন না করলে আপনার ঈদ doesn't feel like ঈদ?",
    "options": [
      "ট্রাক ভাড়া না করলে",
      "dj বাহারুলের গান না বাজালে",
      "চুল কালার না করলে",
      "\"সারাদিন ঘুমিয়ে কাটালাম\" লিখে post না করলে"
    ],
    "answer": 4
  },
  {
    "id": 25,
    "type": "logic",
    "question": "নিচের কোন ডিভাইসের ব্লুটুথ কানেকশন সবথেকে সেরা?",
    "options": [
      "Ronaldo",
      "JBL",
      "i-pod",
      "Oraimo"
    ],
    "answer": 1
  },
  {
    "id": 26,
    "type": "logic",
    "question": "নিচের কোন কারণে আর্জেন্টিনা একটি নারী রাষ্ট্র হওয়া উচিত?",
    "options": [
      "থ্রিপিস পরতে পছন্দ করে বলে",
      "ফিফার অবৈধ স্ত্রী বলে",
      "AFA বলে",
      "পুরুষ হওয়া উচিত, কারণ ফ্যানরা আব্বা ডাকে"
    ],
    "answer": 4
  },
  {
    "id": 27,
    "type": "logic",
    "question": "নিচের কে পরবর্তী প্রধানমন্ত্রী হিসেবে সবচেয়ে বেশি দাবিদার?",
    "options": [
      "ড. শফিকুর রহমান",
      "শেখ হাসিনা",
      "খায়রুল দেওয়ান",
      "তারেক রহমান"
    ],
    "answer": 3
  },
  {
    "id": 28,
    "type": "logic",
    "question": "কার গানে অত্যন্ত deep meaning রয়েছে যা সবার পক্ষে বোঝা সম্ভব নয়?",
    "options": [
      "লালন ফকির",
      "রবিন্দ্রনাথ ঠাকুর",
      "কাজী নজরুল ইসলাম",
      "নারগিস"
    ],
    "answer": 4
  },
  {
    "id": 29,
    "type": "logic",
    "question": "দিনে কর্মী রাতে হর্নি কে?",
    "options": [
      "আপনি",
      "আপনার বন্ধু",
      "খায়রুল দেওয়ান",
      "গেম ডেভলপার"
    ],
    "answer": 3
  },
  {
    "id": 30,
    "type": "logic",
    "question": "পরীক্ষার আগের রাতে পড়ালেখা বাদ দিয়ে যখন আপনি Be Trendy গেইম খেলেন তখন আনাস পীরের কোন বার্তাটি মস্তিষ্ক প্রেরণ করে?",
    "options": [
      "তুই মামা একটাতেও চান্স পাবি না, এইটাই রিয়েলিটি!",
      "এই শালা! তোর সিলেবাস শেষ হইসে?",
      "তোমার সফলতার ভাগিদার সবাই; তোমার ব্যার্থতার ভাগিদার কেউ নয়!",
      "একটা থাবর দেবো শালা!"
    ],
    "answer": 2
  },
  {
    "id": 31,
    "type": "logic",
    "question": "আপনার দেশে তেল আবিস্কৃত হলে নিচের কোন ঘটনা ঘটবে?",
    "options": [
      "ব্যাপক উন্নয়ন হবে।",
      "Feeling Proud American Army, Jhang Ke Maidan Mein Kade Na Harde",
      "Democracy is coming to save you!",
      "Your country's regime must change"
    ],
    "answer": 1
  },
  {
    "id": 32,
    "type": "logic",
    "question": "২৫ ডিসেম্বর তারিখে কে দেশে ফিরেছেন?",
    "options": [
      "শেখ মুজিব",
      "সেন্টা ক্লস",
      "তারেক রহমান",
      "জেবু"
    ],
    "answer": 4
  },
  {
    "id": 33,
    "type": "logic",
    "question": "বাজারে গিয়ে আপনি যখন দেখেন জিনিসপত্রের চরম দাম এবং আপনি কোনো মূল্য না দিয়েই চলে আসেন। কেন?",
    "options": [
      "কারন ইউসুফ সরকার কে চরম মূল্য দিতে হবে",
      "কারণ আপনার পকেটে টাকা নাই",
      "কারণ আপনি পার্টনার ছাড়া কাউকে মূল্য দেন না",
      "কারণ আপনি চোর"
    ],
    "answer": 1
  },
  {
    "id": 34,
    "type": "logic",
    "question": "লাভার হিসেবে কারা সেরা?",
    "options": [
      "বিটিএস লাভার",
      "ফিরি ফায়ার লাভার",
      "ড্যনিশ জিহান লাভার",
      "Be Trendy লাভার"
    ],
    "answer": 4
  },
  {
    "id": 35,
    "type": "logic",
    "question": "তাহসান হারিয়েছে তার আলো জেফার খুঁজে নিলো তার ______?",
    "options": [
      "আলো",
      "কালো",
      "মালো",
      "মোজা"
    ],
    "answer": 2
  },
  {
    "id": 36,
    "type": "logic",
    "question": "দাদার ছিল কিছু বাপের ছিল অল্প, এই নিয়ে পুত্রের বুক ভরা গল্প। কে সেই পুত্র?",
    "options": [
      "Real Madrid",
      "Argentina",
      "Brazil",
      "Barcelona"
    ],
    "answer": 3
  },
  {
    "id": 37,
    "type": "logic",
    "question": "When it's \"ডাকাতি\" competition and you have to pick your teammate.",
    "options": [
      "মাফিয়া মেসি",
      "মোহাম্মদপুর",
      "ব্রাহ্মণবাড়িয়া",
      "আর্জেন্টিনা"
    ],
    "answer": 1
  },
  {
    "id": 38,
    "type": "logic",
    "question": "ব্রাহ্মনবাড়িয়ার মানুষ কিসে সেরা?",
    "options": [
      "শান্তি প্রতিষ্ঠায়",
      "ভাতৃত্বে",
      "কামড়া-কামড়িতে",
      "সবাইকে ভালোবাসতে"
    ],
    "answer": 3
  },
  {
    "id": 39,
    "type": "logic",
    "question": "ইন্ডিয়ার একের পর এক বিশ্বকাপ জয়ের পিছনে কার অবদান সবচেয়ে বেশি?",
    "options": [
      "Captain",
      "Coach",
      "Players",
      "Gay Shah"
    ],
    "answer": 4
  },
  {
    "id": 40,
    "type": "logic",
    "question": "আলভী-ইকরা কান্ডে সবকিছু পর্যালোচনা করলে বোঝা যায়, আসল দোষ কার?",
    "options": [
      "আলভীর",
      "ইকরার",
      "তিথির",
      "আপনার (কারণ আপনি ওদের ফাও অ্যাটেনশন দিসেন)"
    ],
    "answer": 4
  },
  {
    "id": 41,
    "type": "logic",
    "question": "মোহাম্মদপুরে হাঁটার সময় হঠাৎ পেছন থেকে ডাকলে কী করা উচিত?",
    "options": [
      "থেমে হাসি দেওয়া",
      "\"জি ভাই\" বলা",
      "সৃষ্টিকর্তার নাম নেওয়া",
      "মানিব্যাগ হাত দিয়ে ধরে রাখা"
    ],
    "answer": 3
  },
  {
    "id": 42,
    "type": "logic",
    "question": "POV: The question is \"Which Emma is from Hollywood\" but you are in \"বাংলা ১ম পত্র\" exam and you have to choose correct option in MCQ.",
    "options": [
      "Emma Stone",
      "Emma Watson",
      "Emma Myers",
      "Emma Mockery"
    ],
    "answer": 1
  },
  {
    "id": 43,
    "type": "logic",
    "question": "ICC এর পূর্ণরূপ কি?",
    "options": [
      "Indian Cricket Council",
      "International Cow Council",
      "International Cricket Council",
      "International Clown Council"
    ],
    "answer": 1
  },
  {
    "id": 44,
    "type": "logic",
    "question": "বর্তমান পৃথিবীর সবচেয়ে শক্তিশালী আর্মি কোনটি?",
    "options": [
      "ফিলিং প্রাউড ইন্ডিয়ান আর্মি",
      "BTS আর্মি",
      "ফেসবুক বট বাহিনী",
      "সিঙ্গারা কর্মী"
    ],
    "answer": 3
  },
  {
    "id": 45,
    "type": "logic",
    "question": "WW3 শুরু হলে বাংলাদেশ কি দিয়ে যুদ্ধ করবে?",
    "options": [
      "Capcut যোদ্ধা",
      "পারমাণবিক লুঙ্গি",
      "শাহবাগীদের গায়ের গন্ধ",
      "চেতনা"
    ],
    "answer": 1
  },
  {
    "id": 46,
    "type": "logic",
    "question": "বাংলা একাডেমি মনোনীত, বাংলা ভাষার অভিধানে যুক্ত হওয়া তরমুজের নতুন নাম কি?",
    "options": [
      "মধু মধু",
      "রসমালাই",
      "শিরবিনি",
      "পায়েশ"
    ],
    "answer": 1
  },
  {
    "id": 47,
    "type": "logic",
    "question": "বিশ্বে শান্তি প্রতিষ্ঠার জন্য এ বছর কে শান্তিতে নোবেল পাওয়ার দাবি রাখে?",
    "options": [
      "DoLundTrump",
      "জাতিসংঘ",
      "নেতানিয়াহু",
      "কেউ না (কারণ নোবেল জেলে)"
    ],
    "answer": 4
  },
  {
    "id": 48,
    "type": "logic",
    "question": "এবার রমজানে সবার রোযা থাকলেও কার রোযা ছিলোনা?",
    "options": [
      "তাহসান",
      "তাহসান",
      "তাহসান",
      "তাহসান"
    ],
    "answer": 1
  },
  {
    "id": 49,
    "type": "logic",
    "question": "When you are the judge of a Dance Competition and you have to pick best \"নর্তকী\"...",
    "options": [
      "Nora Fatehi",
      "Michael Jackson",
      "Hrithik Roshan",
      "Narendra Modi"
    ],
    "answer": 4
  },
  {
    "id": 50,
    "type": "logic",
    "question": "বর্তমানে ঈদের জন্য বেস্ট আউটফিট কোনটি?",
    "options": [
      "Bootcut formal pent",
      "Mullet haircut",
      "Sequence Panjabi",
      "Teddy shirt"
    ],
    "answer": 1
  },
  {
    "id": 51,
    "type": "logic",
    "question": "২০২০ সালে যদি আপনি টিকটক শুরু করতেন তাহলে আজ আপনার কি থাকতো?",
    "options": [
      "সেলুন",
      "জুতার দোকান",
      "ল্যাম্বর্গিনি",
      "কাপড়ের শোরুম"
    ],
    "answer": 3
  },
  {
    "id": 52,
    "type": "logic",
    "question": "বিশ্বের সবচেয়ে বেশি তেলের যোগান দেয় কোন দেশ?",
    "options": [
      "ইরান",
      "সৌদি আরব",
      "ভেনিজুয়েলা",
      "Random bangu when he needs \"সহ সভাপতি পদ\""
    ],
    "answer": 4
  },
  {
    "id": 53,
    "type": "logic",
    "question": "ছেলেরা আসলে কিসে আটকায়?",
    "options": [
      "নারী",
      "বাড়ি",
      "গাড়ি",
      "RTX 5090"
    ],
    "answer": 4
  },
  {
    "id": 54,
    "type": "logic",
    "question": "ফলের রাজা কে?",
    "options": [
      "কাঁঠাল",
      "বাঙ্গি",
      "হেয়ারফল",
      "ডাউনফল"
    ],
    "answer": 2
  },
  {
    "id": 55,
    "type": "logic",
    "question": "একটি বাঘের খাঁচায় আপনার মা এবং আপনার বউ ফেঁসে গিয়েছেন। এখন আপনি কাকে আগে বাঁচাবেন?",
    "options": [
      "মা কে",
      "বউ কে",
      "নিজে কে",
      "বাঘ কে"
    ],
    "answer": 4
  },
  {
    "id": 56,
    "type": "logic",
    "question": "নিচের কোন খাবার খেলে মানুষের মৃত্যু সুনিশ্চিত?",
    "options": [
      "কাঁঠালের বার্গার",
      "হারপিক (Majumder)",
      "(Major) ডালিম",
      "ইঁদুরের বিষ"
    ],
    "answer": 3
  },
  {
    "id": 57,
    "type": "logic",
    "question": "নিচের কোন statement টি সঠিক?",
    "options": [
      "আমেরিকা গণতন্ত্র প্রতিষ্ঠার জন্য যুদ্ধ করে",
      "ট্রাম্প ওয়ার্ল্ড পিস মেকার",
      "জাতিসংঘ বিশ্ব শান্তি প্রতিষ্ঠার জন্য কাজ করে",
      ""
    ],
    "answer": 4
  },
  {
    "id": 58,
    "type": "logic",
    "question": "কোন game মানুষের জীবন ধ্বংস করে দেয়?",
    "options": [
      "Game of Thrones",
      "Squid Game",
      "Game that your ex played",
      "Be Trendy Game"
    ],
    "answer": 3
  },
  {
    "id": 59,
    "type": "logic",
    "question": "Lady Gaga এর সস্তা ভার্সন কে?",
    "options": [
      "Xefer",
      "Neha Kakkar",
      "Dhinchak Pooja",
      "Momতাজ"
    ],
    "answer": 1
  },
  {
    "id": 60,
    "type": "logic",
    "question": "Which 11 was \"ABSOLUTE CINEMA\"",
    "options": [
      "9/11 from America",
      "1/11 from Bangladesh",
      "26/11 from India",
      "11 from stranger things"
    ],
    "answer": 4
  },
  {
    "id": 61,
    "type": "logic",
    "question": "It's \"মানবতার ফেরিওয়ালা\" competition. Now choose your hero wisely.",
    "options": [
      "Skylar white from Breaking Bad",
      "Joffery Lanister from Game of Thrones",
      "Homelander from The Boys",
      "Faraz Karim from Daraz"
    ],
    "answer": 4
  },
  {
    "id": 62,
    "type": "logic",
    "question": "বর্তমানে সেরা podcast host কে?",
    "options": [
      "Nafees Salim",
      "Khaled Farhan",
      "Khaled Hassan",
      "Tama Rashid"
    ],
    "answer": 3
  },
  {
    "id": 63,
    "type": "logic",
    "question": "লোকাল বাসে ঠিক কতজন মানুষ হলে হেল্পার মামা will say \"আর উইঠেন না, বাস ভরা\" instead of \"আসেন মামা প্রচুর জায়গা আসে, পুরা খালি বাস\"?",
    "options": [
      "Math error",
      "Horizontal 8",
      "অনির্ণেয়",
      "অসংজ্ঞায়িত"
    ],
    "answer": 2
  },
  {
    "id": 64,
    "type": "logic",
    "question": "\"খেটে নয় চেটে বড় হও\" বাণীতে কে?",
    "options": [
      "সুফি সম্রাট দেওয়ানবাগী",
      "ডট বাবা তামিম ইকবাল",
      "ফাদার অফ দা নেশন",
      "লর্ড মিথুন"
    ],
    "answer": 2
  },
  {
    "id": 65,
    "type": "logic",
    "question": "\"A well spent day in Toronto\" উক্তিটি কোন মহামানবের?",
    "options": [
      "Dolund Tramp",
      "Justin Bieber",
      "Shakib Al Hassan",
      "Nelson Mendela"
    ],
    "answer": 3
  },
  {
    "id": 66,
    "type": "logic",
    "question": "When its about \"উল্টা পাল্টা কাজ করে নিজেকে W women, sigma women মনে করা\" you must go for",
    "options": [
      "Monika Kabir",
      "Begum Rokeya",
      "Urfi Javed",
      "Shahbagi"
    ],
    "answer": 1
  },
  {
    "id": 67,
    "type": "logic",
    "question": "আপনি গ্রামের চাচাতো ভাই হওয়ায় যে সমস্যায় সবচেয়ে বেশি ভুগছেন...",
    "options": [
      "Inlis bugina",
      "\"Kaman asan\" জাতীয় টেক্সট করছি",
      "রক্তিম সরদারের মিম বুঝতে অসুবিধা",
      "সাপুট করলে সাপুট পাচ্ছিনা"
    ],
    "answer": 3
  },
  {
    "id": 68,
    "type": "logic",
    "question": "বাংলাদেশের নিজস্ব অর্থায়নে এবং নিজস্ব টেকনোলজিতে নির্মিত প্রথম আর্টিফিশিয়াল ইন্টেলিজেন্স কোনটি?",
    "options": [
      "DeepSheikh",
      "RajuTeAi",
      "Gawk Gawk",
      "Chu*tGPT"
    ],
    "answer": 2
  },
  {
    "id": 69,
    "type": "logic",
    "question": "Congratulations! অবশেষে আপনি সর্বশেষ এবং সর্বকঠিন প্রশ্নে উপনীত হয়েছেন। আপনার জন্য সর্বশেষ প্রশ্ন - \"সে কেন আপনার হলোনা?\"",
    "options": [
      "",
      "",
      "",
      ""
    ],
    "answer": 1
  }
]